{
  "Rows": 9,
  "Cols": 9,
  "LevelItemData": [
    { "ItemType": 1, "Color": 1, "LayerCount": 1 },
    { "ItemType": 1, "Color": 2, "LayerCount": 1 },
    { "ItemType": 1, "Color": 3, "LayerCount": 1 },
    { "ItemType": 1, "Color": 4, "LayerCount": 1 },
    { "ItemType": 1, "Color": 1, "LayerCount": 1 },
    { "ItemType": 1, "Color": 2, "LayerCount": 1 },
    { "ItemType": 1, "Color": 3, "LayerCount": 1 },
    { "ItemType": 1, "Color": 4, "LayerCount": 1 },
    { "ItemType": 1, "Color": 1, "LayerCount": 1 },

    { "ItemType": 1, "Color": 1, "LayerCount": 1 },
    { "ItemType": 1, "Color": 3, "LayerCount": 1 },
    { "ItemType": 1, "Color": 4, "LayerCount": 1 },
    { "ItemType": 1, "Color": 1, "LayerCount": 1 },
    { "ItemType": 1, "Color": 2, "LayerCount": 1 },
    { "ItemType": 1, "Color": 3, "LayerCount": 1 },
    { "ItemType": 1, "Color": 4, "LayerCount": 1 },
    { "ItemType": 1, "Color": 1, "LayerCount": 2 },
    { "ItemType": 1, "Color": 2, "LayerCount": 1 },

    { "ItemType": 1, "Color": 3, "LayerCount": 1 },
    { "ItemType": 1, "Color": 4, "LayerCount": 1 },
    { "ItemType": 1, "Color": 1, "LayerCount": 1 },
    { "ItemType": 1, "Color": 2, "LayerCount": 1 },
    { "ItemType": 1, "Color": 3, "LayerCount": 1 },
    { "ItemType": 1, "Color": 4, "LayerCount": 1 },
    { "ItemType": 1, "Color": 1, "LayerCount": 1 },
    { "ItemType": 1, "Color": 2, "LayerCount": 1 },
    { "ItemType": 1, "Color": 3, "LayerCount": 1 },

    { "ItemType": 1, "Color": 4, "LayerCount": 1 },
    { "ItemType": 1, "Color": 1, "LayerCount": 1 },
    { "ItemType": 1, "Color": 2, "LayerCount": 1 },
    { "ItemType": 1, "Color": 3, "LayerCount": 1 },
    { "ItemType": 1, "Color": 4, "LayerCount": 1 },
    { "ItemType": 1, "Color": 1, "LayerCount": 1 },
    { "ItemType": 1, "Color": 2, "LayerCount": 1 },
    { "ItemType": 1, "Color": 3, "LayerCount": 1 },
    { "ItemType": 1, "Color": 4, "LayerCount": 1 },

    { "ItemType": 1, "Color": 1, "LayerCount": 1 },
    { "ItemType": 1, "Color": 2, "LayerCount": 1 },
    { "ItemType": 1, "Color": 3, "LayerCount": 1 },
    { "ItemType": 1, "Color": 4, "LayerCount": 1 },
    { "ItemType": 1, "Color": 1, "LayerCount": 1 },
    { "ItemType": 1, "Color": 2, "LayerCount": 1 },
    { "ItemType": 1, "Color": 3, "LayerCount": 1 },
    { "ItemType": 1, "Color": 4, "LayerCount": 1 },
    { "ItemType": 1, "Color": 1, "LayerCount": 1 },

    { "ItemType": 1, "Color": 2, "LayerCount": 1 },
    { "ItemType": 1, "Color": 3, "LayerCount": 1 },
    { "ItemType": 1, "Color": 4, "LayerCount": 1 },
    { "ItemType": 1, "Color": 1, "LayerCount": 1 },
    { "ItemType": 1, "Color": 2, "LayerCount": 1 },
    { "ItemType": 1, "Color": 3, "LayerCount": 1 },
    { "ItemType": 1, "Color": 4, "LayerCount": 1 },
    { "ItemType": 1, "Color": 1, "LayerCount": 1 },
    { "ItemType": 1, "Color": 2, "LayerCount": 1 },

    { "ItemType": 1, "Color": 3, "LayerCount": 1 },
    { "ItemType": 1, "Color": 4, "LayerCount": 1 },
    { "ItemType": 1, "Color": 1, "LayerCount": 1 },
    { "ItemType": 1, "Color": 2, "LayerCount": 1 },
    { "ItemType": 1, "Color": 3, "LayerCount": 1 },
    { "ItemType": 1, "Color": 4, "LayerCount": 1 },
    { "ItemType": 1, "Color": 1, "LayerCount": 1 },
    { "ItemType": 1, "Color": 2, "LayerCount": 1 },
    { "ItemType": 1, "Color": 3, "LayerCount": 1 },

    { "ItemType": 1, "Color": 4, "LayerCount": 1 },
    { "ItemType": 1, "Color": 1, "LayerCount": 1 },
    { "ItemType": 1, "Color": 2, "LayerCount": 1 },
    { "ItemType": 1, "Color": 3, "LayerCount": 1 },
    { "ItemType": 1, "Color": 4, "LayerCount": 1 },
    { "ItemType": 1, "Color": 1, "LayerCount": 1 },
    { "ItemType": 1, "Color": 2, "LayerCount": 1 },
    { "ItemType": 1, "Color": 3, "LayerCount": 1 },
    { "ItemType": 1, "Color": 4, "LayerCount": 1 },

    { "ItemType": 1, "Color": 1, "LayerCount": 1 },
    { "ItemType": 1, "Color": 2, "LayerCount": 1 },
    { "ItemType": 1, "Color": 3, "LayerCount": 1 },
    { "ItemType": 1, "Color": 4, "LayerCount": 2 },
    { "ItemType": 1, "Color": 1, "LayerCount": 2 },
    { "ItemType": 1, "Color": 2, "LayerCount": 1 },
    { "ItemType": 1, "Color": 3, "LayerCount": 1 },
    { "ItemType": 1, "Color": 4, "LayerCount": 1 },
    { "ItemType": 1, "Color": 1, "LayerCount": 1 }
  ],
  "GeneratorData": [
    { "ItemType": 1, "Color": 5, "LayerCount": 1 },
    { "ItemType": 1, "Color": 6, "LayerCount": 1 }
  ]
}
